seldon_deploy_sdk/__init__.py
seldon_deploy_sdk/api_client.py
seldon_deploy_sdk/configuration.py
seldon_deploy_sdk/rest.py
seldon_deploy_sdk/api/__init__.py
seldon_deploy_sdk/api/alerting_service_api.py
seldon_deploy_sdk/api/application_logs_api.py
seldon_deploy_sdk/api/batch_jobs_api.py
seldon_deploy_sdk/api/drift_detector_api.py
seldon_deploy_sdk/api/environment_api.py
seldon_deploy_sdk/api/experiments_api.py
seldon_deploy_sdk/api/explain_api.py
seldon_deploy_sdk/api/git_ops_api.py
seldon_deploy_sdk/api/healthcheck_service_api.py
seldon_deploy_sdk/api/inference_logs_service_api.py
seldon_deploy_sdk/api/kubernetes_resources_api.py
seldon_deploy_sdk/api/loadtest_jobs_api.py
seldon_deploy_sdk/api/metrics_server_api.py
seldon_deploy_sdk/api/model_metadata_service_api.py
seldon_deploy_sdk/api/models_api.py
seldon_deploy_sdk/api/monitor_api.py
seldon_deploy_sdk/api/outlier_detector_api.py
seldon_deploy_sdk/api/permission_management_service_api.py
seldon_deploy_sdk/api/pipelines_api.py
seldon_deploy_sdk/api/predict_api.py
seldon_deploy_sdk/api/secrets_service_api.py
seldon_deploy_sdk/api/seldon_deployments_api.py
seldon_deploy_sdk/auth/__init__.py
seldon_deploy_sdk/auth/base.py
seldon_deploy_sdk/auth/openid.py
seldon_deploy_sdk/auth/session.py
seldon_deploy_sdk/models/__init__.py
seldon_deploy_sdk/models/advanced_config.py
seldon_deploy_sdk/models/affinity.py
seldon_deploy_sdk/models/alibi_explainer_type.py
seldon_deploy_sdk/models/application_log.py
seldon_deploy_sdk/models/application_logs_params.py
seldon_deploy_sdk/models/application_logs_response.py
seldon_deploy_sdk/models/audit_log.py
seldon_deploy_sdk/models/aws_elastic_block_store_volume_source.py
seldon_deploy_sdk/models/azure_data_disk_caching_mode.py
seldon_deploy_sdk/models/azure_data_disk_kind.py
seldon_deploy_sdk/models/azure_disk_volume_source.py
seldon_deploy_sdk/models/azure_file_volume_source.py
seldon_deploy_sdk/models/basic_detector_configuration.py
seldon_deploy_sdk/models/batch_job_definition.py
seldon_deploy_sdk-2.4.0.dist-info/METADATA
seldon_deploy_sdk-2.4.0.dist-info/WHEEL
seldon_deploy_sdk-2.4.0.dist-info/top_level.txt
seldon_deploy_sdk-2.4.0.dist-info/RECORD
