Metadata-Version: 2.1
Name: seldon-deploy-sdk
Version: 2.4.0
Summary: Seldon Deploy API
Home-page: https://docs.seldon.ai/seldon-enterprise-platform
Author-email: hello@seldon.io
Keywords: Swagger,Seldon Deploy API
Requires-Dist: certifi>=2017.4.17
Requires-Dist: python-dateutil>=2.1
Requires-Dist: six>=1.10
Requires-Dist: urllib3>=1.23
Requires-Dist: Authlib<1.1.0,>=1.0.0
Requires-Dist: requests<3.0.0,>=2.0.0
